dj_utils/__init__.py
dj_utils/apps.py
dj_utils/models.py
dj_utils/tests.py
dj_utils/views.py
dj_utils/static/dj_utils/css/globals.scss
iq_django_utils-0.1.dist-info/METADATA
iq_django_utils-0.1.dist-info/WHEEL
iq_django_utils-0.1.dist-info/top_level.txt
iq_django_utils-0.1.dist-info/RECORD
